{
  "$schema": "https://developer.microsoft.com/json-schemas/fabric/item/report/definition/visualContainer/2.8.0/schema.json",
  "name": "0ee89e7727c11a60b47e",
  "position": {
    "x": 162.4390243902439,
    "y": 399.51219512195121,
    "z": 4000,
    "height": 300,
    "width": 537.07317073170725,
    "tabOrder": 4000
  },
  "visual": {
    "visualType": "map",
    "query": {
      "queryState": {
        "Category": {
          "projections": [
            {
              "field": {
                "Column": {
                  "Expression": {
                    "SourceRef": {
                      "Entity": "dataset"
                    }
                  },
                  "Property": "Pais"
                }
              },
              "queryRef": "dataset.Pais",
              "nativeQueryRef": "Pais",
              "active": true
            }
          ]
        },
        "Size": {
          "projections": [
            {
              "field": {
                "Aggregation": {
                  "Expression": {
                    "Column": {
                      "Expression": {
                        "SourceRef": {
                          "Entity": "dataset"
                        }
                      },
                      "Property": "Total_Vendas"
                    }
                  },
                  "Function": 0
                }
              },
              "queryRef": "Sum(dataset.Total_Vendas)",
              "nativeQueryRef": "Soma de Total_Vendas"
            }
          ]
        }
      }
    },
    "visualContainerObjects": {
      "title": [
        {
          "properties": {
            "text": {
              "expr": {
                "Literal": {
                  "Value": "'Média de  Total Vendas por Pais'"
                }
              }
            },
            "bold": {
              "expr": {
                "Literal": {
                  "Value": "true"
                }
              }
            },
            "alignment": {
              "expr": {
                "Literal": {
                  "Value": "'center'"
                }
              }
            }
          }
        }
      ]
    },
    "drillFilterOtherVisuals": true
  },
  "filterConfig": {
    "filters": [
      {
        "name": "80ee5ac03190e2a6f2fc",
        "field": {
          "Aggregation": {
            "Expression": {
              "Column": {
                "Expression": {
                  "SourceRef": {
                    "Entity": "dataset"
                  }
                },
                "Property": "Total_Vendas"
              }
            },
            "Function": 0
          }
        },
        "type": "Advanced",
        "filter": {
          "Version": 2,
          "From": [
            {
              "Name": "d",
              "Entity": "dataset",
              "Type": 0
            }
          ],
          "Where": [
            {
              "Condition": {
                "Comparison": {
                  "ComparisonKind": 1,
                  "Left": {
                    "Aggregation": {
                      "Expression": {
                        "Column": {
                          "Expression": {
                            "SourceRef": {
                              "Source": "d"
                            }
                          },
                          "Property": "Total_Vendas"
                        }
                      },
                      "Function": 0
                    }
                  },
                  "Right": {
                    "Literal": {
                      "Value": "250L"
                    }
                  }
                }
              }
            }
          ]
        }
      }
    ]
  }
}